timenorm/__init__.py
timenorm/parser.py
timenorm/types.py
timenorm/resources/label/non-operator.txt
timenorm/resources/label/operator.txt
timenorm/resources/linking_configure/between-indicators.txt
timenorm/resources/linking_configure/date-types.txt
timenorm/resources/linking_configure/timeml-schema.xml
timenorm/resources/linking_configure/timenorm-preannotation-regexes.txt
timenorm/resources/linking_configure/timenorm-schema.xml
timenorm/resources/vocab/char2int.txt
timenorm/resources/vocab/dictionary.json
timenorm/scate/__init__.py
timenorm/scate/neural_parser.py
timenorm_py-0.1.0.dist-info/licenses/LICENSE
timenorm_py-0.1.0.dist-info/licenses/NOTICE
timenorm_py-0.1.0.dist-info/METADATA
timenorm_py-0.1.0.dist-info/WHEEL
timenorm_py-0.1.0.dist-info/top_level.txt
timenorm_py-0.1.0.dist-info/RECORD
