Metadata-Version: 2.4
Name: timenorm-py
Version: 0.1.0
Summary: Python-native temporal expression parser and normalizer
Author: Timenorm Python Contributors
License: Apache-2.0
Project-URL: Homepage, https://github.com/clulab/timenorm
Project-URL: Documentation, https://github.com/clulab/timenorm
Project-URL: Repository, https://github.com/clulab/timenorm
Project-URL: Issues, https://github.com/clulab/timenorm/issues
Keywords: nlp,temporal,time,normalization,parsing
Classifier: Development Status :: 3 - Alpha
Classifier: Intended Audience :: Developers
Classifier: Intended Audience :: Science/Research
Classifier: License :: OSI Approved :: Apache Software License
Classifier: Programming Language :: Python :: 3
Classifier: Programming Language :: Python :: 3.10
Classifier: Programming Language :: Python :: 3.11
Classifier: Programming Language :: Python :: 3.12
Classifier: Topic :: Scientific/Engineering :: Artificial Intelligence
Classifier: Topic :: Text Processing :: Linguistic
Requires-Python: >=3.10
License-File: LICENSE
License-File: NOTICE
Requires-Dist: python-dateutil>=2.8.0
Requires-Dist: tensorflow<3.0.0,>=2.12.0
Requires-Dist: numpy>=1.24.0
Provides-Extra: dev
Requires-Dist: pytest>=7.0.0; extra == "dev"
Requires-Dist: pytest-cov>=4.0.0; extra == "dev"
Requires-Dist: black>=23.0.0; extra == "dev"
Requires-Dist: ruff>=0.1.0; extra == "dev"
Requires-Dist: mypy>=1.0.0; extra == "dev"
Dynamic: license-file
